{"annotator_ids":["annotator_008","annotator_008","annotator_002","annotator_017","annotator_008","annotator_017","annotator_006","annotator_018","annotator_017","annotator_006","annotator_011","annotator_015","annotator_005","annotator_017","annotator_005","annotator_009","annotator_013","annotator_020","annotator_013","annotator_010","annotator_004","annotator_007","annotator_013","annotator_008","annotator_018","annotator_014","annotator_008","annotator_004","annotator_017","annotator_016","annotator_007","annotator_019","annotator_015","annotator_010","annotator_008","annotator_008","annotator_012","annotator_007","annotator_003","annotator_014","annotator_013","annotator_005","annotator_007","annotator_007","annotator_018","annotator_002","annotator_013","annotator_016","annotator_018","annotator_020","annotator_017","annotator_016","annotator_009","annotator_014","annotator_009","annotator_012","annotator_006","annotator_014","annotator_008","annotator_016","annotator_012","annotator_004","annotator_007","annotator_012","annotator_006","annotator_008","annotator_007","annotator_020","annotator_016","annotator_020","annotator_008","annotator_014","annotator_010","annotator_005","annotator_013","annotator_019","annotator_011","annotator_008","annotator_009","annotator_013","annotator_013","annotator_015","annotator_018","annotator_006","annotator_004","annotator_012","annotator_009","annotator_005","annotator_009","annotator_009","annotator_004","annotator_013","annotator_009","annotator_005","annotator_014","annotator_018","annotator_002","annotator_020","annotator_009","annotator_011","annotator_017","annotator_012","annotator_012","annotator_011","annotator_011","annotator_004","annotator_006","annotator_009","annotator_016","annotator_016","annotator_010","annotator_008","annotator_004","annotator_011","annotator_019","annotator_003","annotator_005","annotator_011","annotator_007","annotator_006","annotator_005","annotator_005","annotator_001","annotator_016","annotator_008","annotator_002","annotator_007","annotator_016","annotator_002","annotator_010","annotator_012","annotator_019","annotator_014","annotator_011","annotator_007","annotator_002","annotator_008","annotator_001"],"metadata":{"batch_id":"batch_0","batch_size":138},"prompts":["Complex prompt 0 requiring deep reasoning","Complex prompt 1 requiring deep reasoning","Complex prompt 2 requiring deep reasoning","Complex prompt 3 requiring deep reasoning","Complex prompt 4 requiring deep reasoning","Complex prompt 5 requiring deep reasoning","Complex prompt 6 requiring deep reasoning","Complex prompt 7 requiring deep reasoning","Complex prompt 8 requiring deep reasoning","Complex prompt 9 requiring deep reasoning","Complex prompt 10 requiring deep reasoning","Complex prompt 11 requiring deep reasoning","Complex prompt 12 requiring deep reasoning","Complex prompt 13 requiring deep reasoning","Complex prompt 14 requiring deep reasoning","Complex prompt 15 requiring deep reasoning","Complex prompt 16 requiring deep reasoning","Complex prompt 17 requiring deep reasoning","Complex prompt 18 requiring deep reasoning","Complex prompt 19 requiring deep reasoning","Complex prompt 20 requiring deep reasoning","Complex prompt 21 requiring deep reasoning","Complex prompt 22 requiring deep reasoning","Complex prompt 23 requiring deep reasoning","Complex prompt 24 requiring deep reasoning","Complex prompt 25 requiring deep reasoning","Complex prompt 26 requiring deep reasoning","Complex prompt 27 requiring deep reasoning","Complex prompt 28 requiring deep reasoning","Complex prompt 29 requiring deep reasoning","Complex prompt 30 requiring deep reasoning","Complex prompt 31 requiring deep reasoning","Complex prompt 32 requiring deep reasoning","Complex prompt 33 requiring deep reasoning","Complex prompt 34 requiring deep reasoning","Complex prompt 35 requiring deep reasoning","Complex prompt 36 requiring deep reasoning","Complex prompt 37 requiring deep reasoning","Complex prompt 38 requiring deep reasoning","Complex prompt 39 requiring deep reasoning","Complex prompt 40 requiring deep reasoning","Complex prompt 41 requiring deep reasoning","Complex prompt 42 requiring deep reasoning","Complex prompt 43 requiring deep reasoning","Complex prompt 44 requiring deep reasoning","Complex prompt 45 requiring deep reasoning","Complex prompt 46 requiring deep reasoning","Complex prompt 47 requiring deep reasoning","Complex prompt 48 requiring deep reasoning","Complex prompt 49 requiring deep reasoning","Complex prompt 50 requiring deep reasoning","Complex prompt 51 requiring deep reasoning","Complex prompt 52 requiring deep reasoning","Complex prompt 53 requiring deep reasoning","Complex prompt 54 requiring deep reasoning","Complex prompt 55 requiring deep reasoning","Complex prompt 56 requiring deep reasoning","Complex prompt 57 requiring deep reasoning","Complex prompt 58 requiring deep reasoning","Complex prompt 59 requiring deep reasoning","Complex prompt 60 requiring deep reasoning","Complex prompt 61 requiring deep reasoning","Complex prompt 62 requiring deep reasoning","Complex prompt 63 requiring deep reasoning","Complex prompt 64 requiring deep reasoning","Complex prompt 65 requiring deep reasoning","Complex prompt 66 requiring deep reasoning","Complex prompt 67 requiring deep reasoning","Complex prompt 68 requiring deep reasoning","Complex prompt 69 requiring deep reasoning","Complex prompt 70 requiring deep reasoning","Complex prompt 71 requiring deep reasoning","Complex prompt 72 requiring deep reasoning","Complex prompt 73 requiring deep reasoning","Complex prompt 74 requiring deep reasoning","Complex prompt 75 requiring deep reasoning","Complex prompt 76 requiring deep reasoning","Complex prompt 77 requiring deep reasoning","Complex prompt 78 requiring deep reasoning","Complex prompt 79 requiring deep reasoning","Complex prompt 80 requiring deep reasoning","Complex prompt 81 requiring deep reasoning","Complex prompt 82 requiring deep reasoning","Complex prompt 83 requiring deep reasoning","Complex prompt 84 requiring deep reasoning","Complex prompt 85 requiring deep reasoning","Complex prompt 86 requiring deep reasoning","Complex prompt 87 requiring deep reasoning","Complex prompt 88 requiring deep reasoning","Complex prompt 89 requiring deep reasoning","Complex prompt 90 requiring deep reasoning","Complex prompt 91 requiring deep reasoning","Complex prompt 92 requiring deep reasoning","Complex prompt 93 requiring deep reasoning","Complex prompt 94 requiring deep reasoning","Complex prompt 95 requiring deep reasoning","Complex prompt 96 requiring deep reasoning","Complex prompt 97 requiring deep reasoning","Complex prompt 98 requiring deep reasoning","Complex prompt 99 requiring deep reasoning","Complex prompt 100 requiring deep reasoning","Complex prompt 101 requiring deep reasoning","Complex prompt 102 requiring deep reasoning","Complex prompt 103 requiring deep reasoning","Complex prompt 104 requiring deep reasoning","Complex prompt 105 requiring deep reasoning","Complex prompt 106 requiring deep reasoning","Complex prompt 107 requiring deep reasoning","Complex prompt 108 requiring deep reasoning","Complex prompt 109 requiring deep reasoning","Complex prompt 110 requiring deep reasoning","Complex prompt 111 requiring deep reasoning","Complex prompt 112 requiring deep reasoning","Complex prompt 113 requiring deep reasoning","Complex prompt 114 requiring deep reasoning","Complex prompt 115 requiring deep reasoning","Complex prompt 116 requiring deep reasoning","Complex prompt 117 requiring deep reasoning","Complex prompt 118 requiring deep reasoning","Complex prompt 119 requiring deep reasoning","Complex prompt 120 requiring deep reasoning","Complex prompt 121 requiring deep reasoning","Complex prompt 122 requiring deep reasoning","Complex prompt 123 requiring deep reasoning","Complex prompt 124 requiring deep reasoning","Complex prompt 125 requiring deep reasoning","Complex prompt 126 requiring deep reasoning","Complex prompt 127 requiring deep reasoning","Complex prompt 128 requiring deep reasoning","Complex prompt 129 requiring deep reasoning","Complex prompt 130 requiring deep reasoning","Complex prompt 131 requiring deep reasoning","Complex prompt 132 requiring deep reasoning","Complex prompt 133 requiring deep reasoning","Complex prompt 134 requiring deep reasoning","Complex prompt 135 requiring deep reasoning","Complex prompt 136 requiring deep reasoning","Complex prompt 137 requiring deep reasoning"],"responses":["Detailed response 0 with multiple considerations","Detailed response 1 with multiple considerations","Detailed response 2 with multiple considerations","Detailed response 3 with multiple considerations","Detailed response 4 with multiple considerations","Detailed response 5 with multiple considerations","Detailed response 6 with multiple considerations","Detailed response 7 with multiple considerations","Detailed response 8 with multiple considerations","Detailed response 9 with multiple considerations","Detailed response 10 with multiple considerations","Detailed response 11 with multiple considerations","Detailed response 12 with multiple considerations","Detailed response 13 with multiple considerations","Detailed response 14 with multiple considerations","Detailed response 15 with multiple considerations","Detailed response 16 with multiple considerations","Detailed response 17 with multiple considerations","Detailed response 18 with multiple considerations","Detailed response 19 with multiple considerations","Detailed response 20 with multiple considerations","Detailed response 21 with multiple considerations","Detailed response 22 with multiple considerations","Detailed response 23 with multiple considerations","Detailed response 24 with multiple considerations","Detailed response 25 with multiple considerations","Detailed response 26 with multiple considerations","Detailed response 27 with multiple considerations","Detailed response 28 with multiple considerations","Detailed response 29 with multiple considerations","Detailed response 30 with multiple considerations","Detailed response 31 with multiple considerations","Detailed response 32 with multiple considerations","Detailed response 33 with multiple considerations","Detailed response 34 with multiple considerations","Detailed response 35 with multiple considerations","Detailed response 36 with multiple considerations","Detailed response 37 with multiple considerations","Detailed response 38 with multiple considerations","Detailed response 39 with multiple considerations","Detailed response 40 with multiple considerations","Detailed response 41 with multiple considerations","Detailed response 42 with multiple considerations","Detailed response 43 with multiple considerations","Detailed response 44 with multiple considerations","Detailed response 45 with multiple considerations","Detailed response 46 with multiple considerations","Detailed response 47 with multiple considerations","Detailed response 48 with multiple considerations","Detailed response 49 with multiple considerations","Detailed response 50 with multiple considerations","Detailed response 51 with multiple considerations","Detailed response 52 with multiple considerations","Detailed response 53 with multiple considerations","Detailed response 54 with multiple considerations","Detailed response 55 with multiple considerations","Detailed response 56 with multiple considerations","Detailed response 57 with multiple considerations","Detailed response 58 with multiple considerations","Detailed response 59 with multiple considerations","Detailed response 60 with multiple considerations","Detailed response 61 with multiple considerations","Detailed response 62 with multiple considerations","Detailed response 63 with multiple considerations","Detailed response 64 with multiple considerations","Detailed response 65 with multiple considerations","Detailed response 66 with multiple considerations","Detailed response 67 with multiple considerations","Detailed response 68 with multiple considerations","Detailed response 69 with multiple considerations","Detailed response 70 with multiple considerations","Detailed response 71 with multiple considerations","Detailed response 72 with multiple considerations","Detailed response 73 with multiple considerations","Detailed response 74 with multiple considerations","Detailed response 75 with multiple considerations","Detailed response 76 with multiple considerations","Detailed response 77 with multiple considerations","Detailed response 78 with multiple considerations","Detailed response 79 with multiple considerations","Detailed response 80 with multiple considerations","Detailed response 81 with multiple considerations","Detailed response 82 with multiple considerations","Detailed response 83 with multiple considerations","Detailed response 84 with multiple considerations","Detailed response 85 with multiple considerations","Detailed response 86 with multiple considerations","Detailed response 87 with multiple considerations","Detailed response 88 with multiple considerations","Detailed response 89 with multiple considerations","Detailed response 90 with multiple considerations","Detailed response 91 with multiple considerations","Detailed response 92 with multiple considerations","Detailed response 93 with multiple considerations","Detailed response 94 with multiple considerations","Detailed response 95 with multiple considerations","Detailed response 96 with multiple considerations","Detailed response 97 with multiple considerations","Detailed response 98 with multiple considerations","Detailed response 99 with multiple considerations","Detailed response 100 with multiple considerations","Detailed response 101 with multiple considerations","Detailed response 102 with multiple considerations","Detailed response 103 with multiple considerations","Detailed response 104 with multiple considerations","Detailed response 105 with multiple considerations","Detailed response 106 with multiple considerations","Detailed response 107 with multiple considerations","Detailed response 108 with multiple considerations","Detailed response 109 with multiple considerations","Detailed response 110 with multiple considerations","Detailed response 111 with multiple considerations","Detailed response 112 with multiple considerations","Detailed response 113 with multiple considerations","Detailed response 114 with multiple considerations","Detailed response 115 with multiple considerations","Detailed response 116 with multiple considerations","Detailed response 117 with multiple considerations","Detailed response 118 with multiple considerations","Detailed response 119 with multiple considerations","Detailed response 120 with multiple considerations","Detailed response 121 with multiple considerations","Detailed response 122 with multiple considerations","Detailed response 123 with multiple considerations","Detailed response 124 with multiple considerations","Detailed response 125 with multiple considerations","Detailed response 126 with multiple considerations","Detailed response 127 with multiple considerations","Detailed response 128 with multiple considerations","Detailed response 129 with multiple considerations","Detailed response 130 with multiple considerations","Detailed response 131 with multiple considerations","Detailed response 132 with multiple considerations","Detailed response 133 with multiple considerations","Detailed response 134 with multiple considerations","Detailed response 135 with multiple considerations","Detailed response 136 with multiple considerations","Detailed response 137 with multiple considerations"],"rewards":[0.9064307492084569,0.8610838219407856,0.6374800430206413,0.6462496348189006,0.9020328409603755,0.6482432968382175,0.7789542803799926,0.6001499902512331,0.8280616285323606,0.6785971045128905,0.9267108040323615,0.6568103053411501,0.7066748045107931,0.8241219820923813,0.8899709768226703,0.7637333491895462,0.6919872694968036,0.7591172456707,0.7159619547411793,0.6243154935578706,0.7210653039763251,0.7711712652169742,0.861385395301222,0.7972991527470343,0.8972692785762976,0.7360823058098844,0.6371241926585229,0.7168556348855337,0.6016211859016731,0.8767884377279171,0.6065766777444777,0.8047266380000533,0.7391431514997455,0.7116515609503289,0.7348363194294016,0.7708192564912755,0.8905258568514027,0.71628627239127,0.7629327915654617,0.7998445698836504,0.6685648615354861,0.8530285959894853,0.7321972664028639,0.6257032471994307,0.7317626585861011,0.9444964647360381,0.9242951092856564,0.8224653007578405,0.6691831562368395,0.8811078657663924,0.6641174521805766,0.7351674443265332,0.8237417445968087,0.6860403182574552,0.923603907069932,0.923524179151571,0.6368203472637036,0.6197833647371479,0.8619595560427918,0.6994006190240034,0.9464488706365293,0.7922397012980473,0.9442573485353737,0.7560362737011318,0.9316297919063722,0.6797831626048098,0.7137861328960389,0.7389299029352274,0.8207335809871986,0.6965362143392321,0.9467139320929763,0.6355827083838577,0.9040112325773222,0.6103241523385281,0.7405412545254395,0.7329530657729055,0.8034312214117952,0.8181299113294699,0.70876715307241,0.7094180898203439,0.8360658594552829,0.7161469212269683,0.9253769416848838,0.6859525231680952,0.8462483935637427,0.7023257633860462,0.7873655531829648,0.6762554555757606,0.9001173933177633,0.6777763669357388,0.7128090344201835,0.7963644260035245,0.7299832775621924,0.9041126690864454,0.7631511286741725,0.6257321934108049,0.7038440410467711,0.9160380042683702,0.7040531948058877,0.9245269977705384,0.6558559207922768,0.9183714756058641,0.6406758260284149,0.9486435808249221,0.9368464397917093,0.8352588027210388,0.752380525987958,0.916493047365089,0.808637156151433,0.7352727869309563,0.7431284609315415,0.6529214065086149,0.6195747221020615,0.7295073062951807,0.8253872901855573,0.9058998557030697,0.6098484792767479,0.6740142634384072,0.7478487302007503,0.9352264068830662,0.8292828776157557,0.766841517555849,0.9074819872110677,0.8328687406028302,0.6751521793787292,0.6303373483274982,0.7782869266885001,0.7557200499373835,0.7286367139767301,0.6100455113870005,0.6376025940249976,0.7748001556817111,0.9162131064745891,0.8016067284487464,0.6267224735990243,0.7592813255526331,0.7019886953019023,0.8192519376547386],"timestamp":1754832149.5920126}